nonebot_plugin_zhichang/__init__.py
nonebot_plugin_zhichang-1.0.4.dist-info/METADATA
nonebot_plugin_zhichang-1.0.4.dist-info/WHEEL
nonebot_plugin_zhichang-1.0.4.dist-info/RECORD
